rastachimp/__init__.py
rastachimp/rastachimp.py
rastachimp/utils.py
rastachimp-0.3.dist-info/LICENSE.txt
rastachimp-0.3.dist-info/METADATA
rastachimp-0.3.dist-info/WHEEL
rastachimp-0.3.dist-info/top_level.txt
rastachimp-0.3.dist-info/RECORD
