Metadata-Version: 2.1
Name: rastachimp
Version: 0.3
Summary: Tools for topological processing of polygons vectorized from rasters
Home-page: https://github.com/gvellut/rastachimp
Author: Guilhem Vellut
Author-email: g@vellut.com
License: MIT
Project-URL: Bug Reports, https://github.com/gvellut/rastachimp/issues
Project-URL: Source, https://github.com/gvellut/rastachimp
Keywords: gis raster vector data
Platform: UNKNOWN
Classifier: Development Status :: 3 - Alpha
Classifier: Intended Audience :: Developers
Classifier: Intended Audience :: Information Technology
Classifier: Intended Audience :: Science/Research
Classifier: License :: OSI Approved :: MIT License
Classifier: Programming Language :: Python :: 3
Classifier: Operating System :: OS Independent
Classifier: Topic :: Scientific/Engineering :: GIS
Requires-Dist: shapely (>=1.6)
Requires-Dist: rtree
Requires-Dist: numba
Provides-Extra: dev
Requires-Dist: black (>=18) ; extra == 'dev'
Requires-Dist: isort ; extra == 'dev'
Requires-Dist: flake8 (>=3.6) ; extra == 'dev'
Requires-Dist: sphinx ; extra == 'dev'
Requires-Dist: twine ; extra == 'dev'
Requires-Dist: pytest (>=4) ; extra == 'dev'
Requires-Dist: rasterio ; extra == 'dev'
Requires-Dist: fiona ; extra == 'dev'
